datana/__init__.py
datana/atom.py
datana/dos.py
datana/dynamic.py
datana/figure.py
datana/plotting.py
datana/spectrum.py
datana/structure.py
datana-0.3.1.3.dist-info/METADATA
datana-0.3.1.3.dist-info/WHEEL
datana-0.3.1.3.dist-info/top_level.txt
datana-0.3.1.3.dist-info/RECORD
