Metadata-Version: 2.1
Name: datana
Version: 0.3.1.3
Summary: datana pakage
Home-page: https://github.com/MasterLegend/datana
Author: MasterLegend
License: UNKNOWN
Platform: UNKNOWN
